{
  "metadata": {
    "scraped_at": "2026-07-09T20:39:01.771587+00:00",
    "subject": "SLPA",
    "subject_title": "Speech-Language Pathology",
    "total_courses": 18,
    "scraper_version": "memory-safe-v2.0"
  },
  "courses": [
    {
      "subject": "SLPA",
      "course_code": "5101",
      "title": "Professional Development and Ethics I",
      "credits": "1.00",
      "terms": [
        {
          "term_code": "2420",
          "term_name": "2026-27 Term 1",
          "schedule": [
            {
              "section": "--LEC (2464)",
              "meetings": [
                {
                  "time": "Mo 1:30PM - 3:15PM",
                  "location": "Wu Ho Man Yuen Bldg 406",
                  "instructor": "Professor LAW Thomas Ka Tung",
                  "dates": "7/9, 14/9, 21/9, 28/9, 5/10, 12/10"
                },
                {
                  "time": "Mo 1:30PM - 3:15PM",
                  "location": "Wu Ho Man Yuen Bldg 406",
                  "instructor": "Professor LAW Thomas Ka Tung",
                  "dates": "26/10, 2/11, 9/11, 16/11, 23/11, 30/11, 7/12"
                }
              ],
              "availability": {
                "capacity": "63",
                "enrolled": "62",
                "waitlist_capacity": "0",
                "waitlist_total": "0",
                "available_seats": "1",
                "status": "Open"
              },
              "class_attributes": "English only"
            }
          ]
        }
      ],
      "description": "Speech therapy is more than just clinical skills and practice. A competent speech therapist should understand the range of professional issues related to speech-language pathology which may contribute and influence their clinical practice, decision making as well as the profession. Professional issues, ethical principles and practice are introduced and illustrated by the use of case studies and discussions. Students are also introduced to applying the range of principles to ethical practice and decision making.",
      "enrollment_requirement": "For students in MSc Speech-Language Pathology",
      "course_attributes": "",
      "academic_career": "Postgraduate - Taught",
      "grading_basis": "Graded",
      "component": "Lecture",
      "campus": "Main Campus",
      "academic_group": "Div of ORL & Commn Science",
      "academic_org": "Div of ORL & Commn Science",
      "learning_outcomes": "Upon completion of this course, students will be able to understand the concept of professional development and ethics",
      "course_syllabus": "The course outline, including the course syllabus, will be provided to students in their first week of attendance in this course.",
      "assessment_types": {},
      "feedback_evaluation": "Students are encouraged to communicate with the instructors to provide comments and/or feedback on the course. Students are requested to participate in the term-end course evaluation.",
      "required_readings": "The course outline, including the list of required/recommended readings, will be provided to students in their first week of attendance in this course.",
      "recommended_readings": ""
    },
    {
      "subject": "SLPA",
      "course_code": "5103",
      "title": "Evidence Based Appraisal for Speech Language Pathology I",
      "credits": "2.00",
      "terms": [
        {
          "term_code": "2430",
          "term_name": "2026-27 Term 2",
          "schedule": [
            {
              "section": "--LEC (2421)",
              "meetings": [
                {
                  "time": "Th 8:30AM - 11:15AM",
                  "location": "Wu Ho Man Yuen Bldg 403",
                  "instructor": "Dr. NG Hoi Yee Iris",
                  "dates": "18/2, 25/2, 4/3, 11/3, 18/3, 25/3, 1/4, 8/4, 15/4"
                }
              ],
              "availability": {
                "capacity": "63",
                "enrolled": "62",
                "waitlist_capacity": "0",
                "waitlist_total": "0",
                "available_seats": "1",
                "status": "Open"
              },
              "class_attributes": "Cantonese and English"
            }
          ]
        }
      ],
      "description": "This course covers basic methodology in research design in the behavioral sciences and basic statistical tools and techniques for analyzing experimental data. Knowledge and procedures of critical appraisal in the practice of evidence-based health care will be introduced. Approaches to evaluate the effectiveness and efficiency of clinical programmes are covered.",
      "enrollment_requirement": "For students in MSc Speech-Language Pathology",
      "course_attributes": "",
      "academic_career": "Postgraduate - Taught",
      "grading_basis": "Graded",
      "component": "Lecture",
      "campus": "Main Campus",
      "academic_group": "Div of ORL & Commn Science",
      "academic_org": "Div of ORL & Commn Science",
      "learning_outcomes": "Upon completion of this course, students will be able to:\n1. Understand the research methodology for Speech Language Pathology\n2. Be able to use basic statistical tools for analyzing experimental data\n3. Acquire the knowledge and procedures of critical appraisal in the practice of evidence-based health care",
      "course_syllabus": "The course outline, including the course syllabus, will be provided to students in their first week of attendance in this course.",
      "assessment_types": {},
      "feedback_evaluation": "Students are encouraged to communicate with the instructors to provide comments and/or feedback on the course. Students are requested to participate in the term-end course evaluation.",
      "required_readings": "The course outline, including the list of required/recommended readings, will be provided to students in their first week of attendance in this course.",
      "recommended_readings": ""
    },
    {
      "subject": "SLPA",
      "course_code": "5105",
      "title": "Test Development & Assessment Approaches",
      "credits": "2.00",
      "terms": [
        {
          "term_code": "2450",
          "term_name": "2026-27 Summer Session",
          "schedule": [
            {
              "section": "A-LEC (1012)",
              "meetings": [
                {
                  "time": "Mo 9:30AM - 12:15PM",
                  "location": "Wu Ho Man Yuen Bldg 304",
                  "instructor": "Dr. NG Hoi Yee Iris, \nDr. YU Shing",
                  "dates": "3/5, 10/5, 17/5, 24/5, 31/5, 7/6, 14/6, 21/6, 28/6"
                }
              ],
              "availability": {
                "capacity": "63",
                "enrolled": "62",
                "waitlist_capacity": "0",
                "waitlist_total": "0",
                "available_seats": "1",
                "status": "Open"
              },
              "class_attributes": "Cantonese and English"
            },
            {
              "section": "B-LEC (1011)",
              "meetings": [
                {
                  "time": "Mo 2:30PM - 5:15PM",
                  "location": "Wu Ho Man Yuen Bldg 304",
                  "instructor": "Staff",
                  "dates": "17/5, 24/5, 31/5, 7/6, 14/6, 21/6, 28/6"
                }
              ],
              "availability": {
                "capacity": "63",
                "enrolled": "0",
                "waitlist_capacity": "0",
                "waitlist_total": "0",
                "available_seats": "63",
                "status": "Open"
              },
              "class_attributes": "Cantonese and English"
            }
          ]
        }
      ],
      "description": "Assessment is a major component in the study of speech-language pathology. This course will introduce key assessment approaches including norm-referenced, criterion-referenced and dynamic tests. Students will learn about the characteristics of each type of assessment, the meaningful interpretation of test scores as well as the potential application in communication disorders in culturally and linguistically diverse populations. Students will learn major procedures in test development from item construction to data collection to evaluation. Critical concepts of psychometric properties of test evaluation will be covered.",
      "enrollment_requirement": "For students in MSc Speech-Language Pathology",
      "course_attributes": "",
      "academic_career": "Postgraduate - Taught",
      "grading_basis": "Graded",
      "component": "Lecture",
      "campus": "Main Campus",
      "academic_group": "Div of ORL & Commn Science",
      "academic_org": "Div of ORL & Commn Science",
      "learning_outcomes": "Upon completion of this course, students will be able to:\n1. Demonstrate the ability to identify and locate major anatomical structures related respiration, swallowing, speech, language and hearing\n2. Explain the physiological function(s) of anatomical structures related to respiration, swallowing, speech, language and hearing\n3. Demonstrate a basic understanding of the nervous system and neural sub-systems\n4. Understand and explain the physiological relationship(s) between the nervous system and the relevant neural structures related to speech.",
      "course_syllabus": "Please refer to the course outline",
      "assessment_types": {},
      "feedback_evaluation": "Please refer to the course outline",
      "required_readings": "Please refer to the course outline",
      "recommended_readings": "Please refer to the course outline"
    },
    {
      "subject": "SLPA",
      "course_code": "5106",
      "title": "Anatomy and Physiology of Speech, Language and Hearing",
      "credits": "3.00",
      "terms": [
        {
          "term_code": "2420",
          "term_name": "2026-27 Term 1",
          "schedule": [
            {
              "section": "A-LEC (1211)",
              "meetings": [
                {
                  "time": "We 9:30AM - 12:15PM",
                  "location": "Wu Ho Man Yuen Bldg 508",
                  "instructor": "Professor FONG Raymond",
                  "dates": "9/9, 16/9, 23/9, 30/9, 7/10, 14/10, 21/10, 28/10, 4/11, 11/11, 18/11, 25/11, 2/12"
                }
              ],
              "availability": {
                "capacity": "70",
                "enrolled": "35",
                "waitlist_capacity": "0",
                "waitlist_total": "0",
                "available_seats": "35",
                "status": "Open"
              },
              "class_attributes": "English only"
            }
          ]
        }
      ],
      "description": "An introduction to the anatomical and physiological aspects to the auditory, respiratory, laryngeal, and swallowing systems is provided. There will be lectures, in-class activities and laboratory sessions. Students will be exposed to anatomy and physiology software, 3D models and the 3D Anatomage Table (life-sized visualization system) to enhance learning.",
      "enrollment_requirement": "For students in MSc Speech-Language Pathology and BA Bimodal Bilingual Studies",
      "course_attributes": "",
      "academic_career": "Postgraduate - Taught",
      "grading_basis": "Graded",
      "component": "Lecture",
      "campus": "Main Campus",
      "academic_group": "Div of ORL & Commn Science",
      "academic_org": "Div of ORL & Commn Science",
      "learning_outcomes": "Upon completion of this course, students will be able to:\n1. Demonstrate the ability to identify and locate major anatomical structures related respiration, swallowing, speech, language and hearing\n2. Explain the physiological function(s) of anatomical structures related to respiration, swallowing, speech, language and hearing\n3. Demonstrate a basic understanding of the nervous system and neural sub-systems\n4. Understand and explain the physiological relationship(s) between the nervous system and the relevant neural structures related to speech.",
      "course_syllabus": "Please refer to the course outline",
      "assessment_types": {},
      "feedback_evaluation": "Please refer to the course outline",
      "required_readings": "Please refer to the course outline",
      "recommended_readings": ""
    },
    {
      "subject": "SLPA",
      "course_code": "5201",
      "title": "Fluency Disorders",
      "credits": "3.00",
      "terms": [
        {
          "term_code": "2420",
          "term_name": "2026-27 Term 1",
          "schedule": [
            {
              "section": "--LEC (2463)",
              "meetings": [
                {
                  "time": "Mo 8:30AM - 11:15AM",
                  "location": "Esther Lee Bldg 307",
                  "instructor": "Professor LAW Thomas Ka Tung",
                  "dates": "7/9, 14/9, 21/9, 28/9, 5/10, 12/10"
                },
                {
                  "time": "Mo 8:30AM - 11:15AM",
                  "location": "Esther Lee Bldg 307",
                  "instructor": "Professor LAW Thomas Ka Tung",
                  "dates": "26/10, 2/11, 9/11, 16/11, 23/11, 30/11, 7/12"
                }
              ],
              "availability": {
                "capacity": "63",
                "enrolled": "62",
                "waitlist_capacity": "0",
                "waitlist_total": "0",
                "available_seats": "1",
                "status": "Open"
              },
              "class_attributes": "Cantonese and English"
            }
          ]
        }
      ],
      "description": "This course discusses the nature, symptoms, and prevalence of stuttering disorders. Students will be provided with the basic knowledge on assessing, counselling, and treating persons with fluency disorders.",
      "enrollment_requirement": "For students in MSc Speech-Language Pathology",
      "course_attributes": "",
      "academic_career": "Postgraduate - Taught",
      "grading_basis": "Graded",
      "component": "Lecture",
      "campus": "Main Campus",
      "academic_group": "Div of ORL & Commn Science",
      "academic_org": "Div of ORL & Commn Science",
      "learning_outcomes": "Upon completion of this course, students will be able to:\n1. Understand the nature, symptoms, and prevalence of fluency disorders\n2. Be able to assess and manage persons with fluency disorders",
      "course_syllabus": "The course outline, including the course syllabus, will be provided to students in their first week of attendance in this course.",
      "assessment_types": {},
      "feedback_evaluation": "Students are encouraged to communicate with the instructors to provide comments and/or feedback on the course. Students are requested to participate in the term-end course evaluation.",
      "required_readings": "The course outline, including the list of required/recommended readings, will be provided to students in their first week of attendance in this course.",
      "recommended_readings": ""
    },
    {
      "subject": "SLPA",
      "course_code": "5203",
      "title": "Acquired Neurogenic Communication Disorders",
      "credits": "4.00",
      "terms": [
        {
          "term_code": "2430",
          "term_name": "2026-27 Term 2",
          "schedule": [
            {
              "section": "--LEC (2291)",
              "meetings": [
                {
                  "time": "We 8:30AM - 12:15PM",
                  "location": "Wu Ho Man Yuen Bldg 305",
                  "instructor": "Ms. KWAN Ching Yin, \nProfessor FONG Raymond",
                  "dates": "6/1, 13/1, 20/1, 27/1, 3/2"
                },
                {
                  "time": "We 8:30AM - 12:15PM",
                  "location": "Wu Ho Man Yuen Bldg 305",
                  "instructor": "Ms. KWAN Ching Yin, \nProfessor FONG Raymond",
                  "dates": "17/2, 24/2, 3/3, 10/3, 17/3, 24/3, 31/3, 7/4, 14/4"
                }
              ],
              "availability": {
                "capacity": "63",
                "enrolled": "62",
                "waitlist_capacity": "0",
                "waitlist_total": "0",
                "available_seats": "1",
                "status": "Open"
              },
              "class_attributes": "Cantonese and English"
            }
          ]
        }
      ],
      "description": "This course gives an overview of the human's nervous system in terms of its structure and function. The primary focus is on the nervous system in the reception and expression of speech and language. Speech and language disorders resulting from cardiovascular and cerebrovascular damage due to trauma, disease and adventitious central nervous system (CNS) events will be included. Evaluation and management of the related language, speech and cognitive disorders will be covered.",
      "enrollment_requirement": "For students in MSc Speech-Language Pathology",
      "course_attributes": "",
      "academic_career": "Postgraduate - Taught",
      "grading_basis": "Graded",
      "component": "Lecture",
      "campus": "Main Campus",
      "academic_group": "Div of ORL & Commn Science",
      "academic_org": "Div of ORL & Commn Science",
      "learning_outcomes": "Upon completion of this course, students will be able to:\n1. Understand the structure and function of the human’s nervous system\n2. Evaluate and manage the related language, speech and cognitive disorders",
      "course_syllabus": "The course outline, including the course syllabus, will be provided to students in their first week of attendance in this course.",
      "assessment_types": {},
      "feedback_evaluation": "Students are encouraged to communicate with the instructors to provide comments and/or feedback on the course. Students are requested to participate in the term-end course evaluation.",
      "required_readings": "The course outline, including the list of required/recommended readings, will be provided to students in their first week of attendance in this course.",
      "recommended_readings": ""
    },
    {
      "subject": "SLPA",
      "course_code": "5204",
      "title": "Complex Communication Needs",
      "credits": "3.00",
      "terms": [
        {
          "term_code": "2430",
          "term_name": "2026-27 Term 2",
          "schedule": [
            {
              "section": "--LEC (2433)",
              "meetings": [
                {
                  "time": "Fr 9:30AM - 12:15PM",
                  "location": "Hui Yeung Shing Bldg G04",
                  "instructor": "Ms LAM Yuk Chau",
                  "dates": "8/1, 15/1, 22/1, 29/1"
                },
                {
                  "time": "Fr 9:30AM - 12:15PM",
                  "location": "Hui Yeung Shing Bldg G04",
                  "instructor": "Ms LAM Yuk Chau",
                  "dates": "12/2, 19/2, 26/2, 5/3, 12/3, 19/3"
                },
                {
                  "time": "Fr 9:30AM - 12:15PM",
                  "location": "Hui Yeung Shing Bldg G04",
                  "instructor": "Ms LAM Yuk Chau",
                  "dates": "2/4, 9/4, 16/4, 23/4, 30/4"
                }
              ],
              "availability": {
                "capacity": "63",
                "enrolled": "62",
                "waitlist_capacity": "0",
                "waitlist_total": "0",
                "available_seats": "1",
                "status": "Open"
              },
              "class_attributes": "Cantonese and English"
            }
          ]
        }
      ],
      "description": "The course introduces the methodologies and technologies used to promote the development of communication skills in individuals with various kinds of communication disorders including cerebral palsy and multiple disabilities. The impact of augmentative communication in social interaction, personal growth, educational & vocational opportunities, as well as other aspects of human interaction will be discussed.",
      "enrollment_requirement": "For students in MSc Speech-Language Pathology",
      "course_attributes": "",
      "academic_career": "Postgraduate - Taught",
      "grading_basis": "Graded",
      "component": "Lecture",
      "campus": "Main Campus",
      "academic_group": "Div of ORL & Commn Science",
      "academic_org": "Div of ORL & Commn Science",
      "learning_outcomes": "Upon completion of this course, students will be able to:\n1. Describe and implement assessment and management strategies for individuals with complex communication needs\n2. Recognize the characteristics of common congenital and acquired disabilities and their impact of communication, and design multimodal communication systems accordingly\n3. Recognize the role of speech-language pathologists among members of the multidisciplinary team in managing clients with complex communication needs",
      "course_syllabus": "Please refer to the course outline",
      "assessment_types": {},
      "feedback_evaluation": "Please refer to the course outline",
      "required_readings": "Please refer to the course outline",
      "recommended_readings": ""
    },
    {
      "subject": "SLPA",
      "course_code": "5205",
      "title": "Language Disorders from Infancy to Adolescence I",
      "credits": "3.00",
      "terms": [
        {
          "term_code": "2420",
          "term_name": "2026-27 Term 1",
          "schedule": [
            {
              "section": "A-LEC (2320)",
              "meetings": [
                {
                  "time": "We 4:30PM - 7:15PM",
                  "location": "Fung King Hey Bldg Swire Hall1",
                  "instructor": "Professor Valerie Jane PEREIRA",
                  "dates": "9/9, 16/9, 23/9, 30/9, 7/10, 14/10, 21/10, 28/10, 4/11, 11/11, 18/11, 25/11, 2/12, 9/12"
                }
              ],
              "availability": {
                "capacity": "63",
                "enrolled": "62",
                "waitlist_capacity": "0",
                "waitlist_total": "0",
                "available_seats": "1",
                "status": "Open"
              },
              "class_attributes": "English only"
            },
            {
              "section": "B-LEC (2321)",
              "meetings": [
                {
                  "time": "We 4:30PM - 7:15PM",
                  "location": "Fung King Hey Bldg Swire Hall2",
                  "instructor": "Professor Valerie Jane PEREIRA",
                  "dates": "16/9, 23/9"
                },
                {
                  "time": "We 4:30PM - 7:15PM",
                  "location": "Fung King Hey Bldg Swire Hall2",
                  "instructor": "Professor Valerie Jane PEREIRA",
                  "dates": "14/10, 21/10"
                },
                {
                  "time": "We 4:30PM - 7:15PM",
                  "location": "Fung King Hey Bldg Swire Hall2",
                  "instructor": "Professor Valerie Jane PEREIRA",
                  "dates": "4/11, 11/11"
                }
              ],
              "availability": {
                "capacity": "63",
                "enrolled": "0",
                "waitlist_capacity": "0",
                "waitlist_total": "0",
                "available_seats": "63",
                "status": "Open"
              },
              "class_attributes": "English only"
            }
          ]
        }
      ],
      "description": "The course focuses on language disorders from infancy to adolescence. The course will expose students to assessment methods and techniques encompassing the three main language domains of form, content and use with direct hands-on experience with relevant and specified standardised and non-standardised assessments. The range of treatment approaches will be covered with an emphasis on evidence-based treatment approaches and practice. Students will also be exposed to person-centred functional goals directly addressing the WHO ICF (International Classification of Functioning, Disability and Health) framework. Teaching and learning enhancement techniques will include case studies, videos and role play.",
      "enrollment_requirement": "For students in MSc Speech-Language Pathology",
      "course_attributes": "",
      "academic_career": "Postgraduate - Taught",
      "grading_basis": "Graded",
      "component": "Lecture",
      "campus": "Main Campus",
      "academic_group": "Div of ORL & Commn Science",
      "academic_org": "Div of ORL & Commn Science",
      "learning_outcomes": "Upon completion of this course, students will be able to:\n1. Identify components of language (form, content and use) and be able to describe and give examples of the typical developmental milestones and skills for each language component at major stages: infancy (pre-linguistic stage), toddlerhood, pre-school, school-age and adolescence.\n2. Identify the relevant standardized assessments for each major stage and domains and discuss other types of assessment methods.\n3. Describe the different types of intervention approaches and identify evidence-based treatment approaches for language components and/or major stages.\n4. Identify and describe considerations in the assessment and treatment of DLD (developmental language disorder), language disorders associated with different conditions (e.g. ASD), bilingual children and in CALD (culturally and linguistically different children).",
      "course_syllabus": "Please refer to the course outline",
      "assessment_types": {},
      "feedback_evaluation": "Please refer to the course outline",
      "required_readings": "Please refer to the course outline",
      "recommended_readings": ""
    },
    {
      "subject": "SLPA",
      "course_code": "5206",
      "title": "Language Disorders from Infancy to Adolescence II",
      "credits": "1.00",
      "terms": [
        {
          "term_code": "2430",
          "term_name": "2026-27 Term 2",
          "schedule": [
            {
              "section": "--LEC (2422)",
              "meetings": [
                {
                  "time": "Th 8:30AM - 11:15AM",
                  "location": "Wu Ho Man Yuen Bldg 403",
                  "instructor": "Professor Valerie Jane PEREIRA",
                  "dates": "7/1, 14/1, 21/1, 28/1, 4/2"
                }
              ],
              "availability": {
                "capacity": "63",
                "enrolled": "62",
                "waitlist_capacity": "0",
                "waitlist_total": "0",
                "available_seats": "1",
                "status": "Open"
              },
              "class_attributes": "English only"
            }
          ]
        }
      ],
      "description": "The course focuses on language disorders from infancy to adolescence. The course will expose students to assessment methods and techniques encompassing the three main language domains of form, content and use with direct hands-on experience with relevant and specified standardised and non-standardised assessments. The range of treatment approaches will be covered with an emphasis on evidence-based treatment approaches and practice. Students will also be exposed to person-centred functional goals directly addressing the WHO ICF (International Classification of Functioning, Disability and Health) framework. Teaching and learning enhancement techniques will include case studies, videos and role play.",
      "enrollment_requirement": "Pre-requisite: SLPA5205\nFor students in MSc Speech-Language Pathology",
      "course_attributes": "",
      "academic_career": "Postgraduate - Taught",
      "grading_basis": "Graded",
      "component": "Lecture",
      "campus": "Main Campus",
      "academic_group": "Div of ORL & Commn Science",
      "academic_org": "Div of ORL & Commn Science",
      "learning_outcomes": "Upon completion of this course, students will be able to:\n1. Identify components of language (form, content and use) and be able to describe and give examples of the typical developmental milestones and skills for each language component at major stages: infancy (pre-linguistic stage), toddlerhood, pre-school, school-age and adolescence.\n2. Identify the relevant standardized assessments for each major stage and domains and discuss other types of assessment methods.\n3. Describe the different types of intervention approaches and identify evidence-based treatment approaches for language components and/or major stages.\n4. Identify and describe considerations in the assessment and treatment of DLD (developmental language disorder), language disorders associated with different conditions (e.g. ASD), bilingual children and in CALD (culturally and linguistically different children).",
      "course_syllabus": "Please refer to the course outline",
      "assessment_types": {},
      "feedback_evaluation": "Please refer to the course outline",
      "required_readings": "Please refer to the course outline",
      "recommended_readings": ""
    },
    {
      "subject": "SLPA",
      "course_code": "5207",
      "title": "Speech Sound Disorders",
      "credits": "3.00",
      "terms": [
        {
          "term_code": "2420",
          "term_name": "2026-27 Term 1",
          "schedule": [
            {
              "section": "--LEC (1210)",
              "meetings": [
                {
                  "time": "Th 3:30PM - 6:15PM",
                  "location": "Yasumoto Int'l Acad Park 403",
                  "instructor": "Professor Valerie Jane PEREIRA",
                  "dates": "10/9, 17/9, 24/9"
                },
                {
                  "time": "Th 3:30PM - 6:15PM",
                  "location": "Yasumoto Int'l Acad Park 403",
                  "instructor": "Professor Valerie Jane PEREIRA",
                  "dates": "8/10, 15/10, 22/10, 29/10, 5/11, 12/11, 19/11, 26/11, 3/12"
                },
                {
                  "time": "Th 3:30PM - 6:15PM",
                  "location": "Hui Yeung Shing Bldg G04",
                  "instructor": "Professor LAW Thomas Ka Tung, \nProfessor Valerie Jane PEREIRA",
                  "dates": "10/12"
                }
              ],
              "availability": {
                "capacity": "63",
                "enrolled": "62",
                "waitlist_capacity": "0",
                "waitlist_total": "0",
                "available_seats": "1",
                "status": "Open"
              },
              "class_attributes": "English only"
            }
          ]
        }
      ],
      "description": "This course covers children's acquisition of speech, articulatory foundations of speech, transcription of speech and classification and causes of speech sound disorders. The course will introduce students to the different types of speech sound disorders, differentiating between those involving phonology (e.g. phonological impairment) and those related to motor speech (e.g. articulation impairment). Students will also be exposed to person-centred functional goals directly addressing the WHO ICF (International Classification of Functioning, Disability and Health) framework. The range of treatment approaches will be taught with an emphasis on evidence-based treatment approaches for the different types of SSD. Teaching and learning enhancement techniques will include case studies, videos and role play/simulations.",
      "enrollment_requirement": "For students in MSc Speech-Language Pathology",
      "course_attributes": "",
      "academic_career": "Postgraduate - Taught",
      "grading_basis": "Graded",
      "component": "Lecture",
      "campus": "Main Campus",
      "academic_group": "Div of ORL & Commn Science",
      "academic_org": "Div of ORL & Commn Science",
      "learning_outcomes": "Upon completion of this course, students will be able to:\n1. Describe the different types of speech sound disorders in children and classification systems used within the field.\n2. Identify appropriate assessment procedure(s) and assessment components and apply the relevant analyses to children's speech.\n3. Discuss the different ways of identifying appropriate goals and identify the most appropriate intervention approach based on the available evidence-base.\n4. Identify considerations for assessing and treating speech sound disorders in selected populations.",
      "course_syllabus": "Please refer to the course outline",
      "assessment_types": {},
      "feedback_evaluation": "Please refer to the course outline",
      "required_readings": "Please refer to the course outline",
      "recommended_readings": ""
    },
    {
      "subject": "SLPA",
      "course_code": "5210",
      "title": "Dysphagia",
      "credits": "3.00",
      "terms": [
        {
          "term_code": "2430",
          "term_name": "2026-27 Term 2",
          "schedule": [
            {
              "section": "--LEC (2434)",
              "meetings": [
                {
                  "time": "Fr 2:30PM - 5:15PM",
                  "location": "Wu Ho Man Yuen Bldg 407",
                  "instructor": "Professor FONG Raymond",
                  "dates": "8/1, 15/1, 22/1, 29/1"
                },
                {
                  "time": "Fr 2:30PM - 5:15PM",
                  "location": "Wu Ho Man Yuen Bldg 407",
                  "instructor": "Professor FONG Raymond",
                  "dates": "12/2, 19/2, 26/2, 5/3, 12/3, 19/3"
                },
                {
                  "time": "Fr 2:30PM - 5:15PM",
                  "location": "Wu Ho Man Yuen Bldg 407",
                  "instructor": "Professor FONG Raymond",
                  "dates": "2/4, 9/4, 16/4, 23/4, 30/4"
                }
              ],
              "availability": {
                "capacity": "64",
                "enrolled": "63",
                "waitlist_capacity": "0",
                "waitlist_total": "0",
                "available_seats": "1",
                "status": "Open"
              },
              "class_attributes": "Cantonese and English"
            }
          ]
        }
      ],
      "description": "This course aims to provide students with the fundamental knowledge of swallowing, dysphagia assessment and management. This course aims to equip students with entry-level skills to assess and manage dysphagia across all age range, in particular the adult population.",
      "enrollment_requirement": "For students in MSc Speech-Language Pathology",
      "course_attributes": "",
      "academic_career": "Postgraduate - Taught",
      "grading_basis": "Graded",
      "component": "Lecture",
      "campus": "Main Campus",
      "academic_group": "Div of ORL & Commn Science",
      "academic_org": "Div of ORL & Commn Science",
      "learning_outcomes": "Upon completion of this course, students will be able to:\n1. Describe the anatomy and physiology in swallowing\n2. Describe the clinical presentation of dysphagia across phases of swallowing\n3. Recognize a range of underlying diseases that can lead to dysphagia and describe the corresponding\npresentation\n4. Differentiate and apply a range of assessments, management and/or therapeutic approaches for dysphagia",
      "course_syllabus": "Please refer to the course outline",
      "assessment_types": {},
      "feedback_evaluation": "Please refer to the course outline",
      "required_readings": "Please refer to the course outline",
      "recommended_readings": ""
    },
    {
      "subject": "SLPA",
      "course_code": "5300",
      "title": "Introduction to Work Integrated Learning and Clinical Practice",
      "credits": "1.00",
      "terms": [
        {
          "term_code": "2420",
          "term_name": "2026-27 Term 1",
          "schedule": [
            {
              "section": "--LEC (2323)",
              "meetings": [
                {
                  "time": "Th 8:30AM - 11:15AM",
                  "location": "Humanities Building 12",
                  "instructor": "Ms KAN Pui Kei Peggy",
                  "dates": "10/9, 17/9"
                },
                {
                  "time": "Th 8:30AM - 11:15AM",
                  "location": "Humanities Building 12",
                  "instructor": "Ms KAN Pui Kei Peggy",
                  "dates": "5/11"
                },
                {
                  "time": "Th 8:30AM - 11:15AM",
                  "location": "Cheng Yu Tung Building 201",
                  "instructor": "Ms KAN Pui Kei Peggy",
                  "dates": "29/10"
                },
                {
                  "time": "Th 8:30AM - 11:15AM",
                  "location": "No Room Required",
                  "instructor": "Ms KAN Pui Kei Peggy",
                  "dates": "24/9, 1/10, 8/10, 15/10, 22/10"
                },
                {
                  "time": "Th 8:30AM - 11:15AM",
                  "location": "No Room Required",
                  "instructor": "Ms KAN Pui Kei Peggy, \nProfessor LAW Thomas Ka Tung",
                  "dates": "12/11, 19/11, 26/11, 3/12"
                }
              ],
              "availability": {
                "capacity": "63",
                "enrolled": "62",
                "waitlist_capacity": "0",
                "waitlist_total": "0",
                "available_seats": "1",
                "status": "Open"
              },
              "class_attributes": "Cantonese and English"
            }
          ]
        }
      ],
      "description": "The course is designed to provide students with basic clinical skills to prepare for clinical practice. Students will acquire basic and generic clinical skills in relation to speech language pathology through seminars, workshops, and simulated learning.",
      "enrollment_requirement": "For students in MSc Speech-Language Pathology",
      "course_attributes": "",
      "academic_career": "Postgraduate - Taught",
      "grading_basis": "Pass/Not Pass",
      "component": "Lecture",
      "campus": "Main Campus",
      "academic_group": "Div of ORL & Commn Science",
      "academic_org": "Div of ORL & Commn Science",
      "learning_outcomes": "Upon completion of this course, students will be able to acquire basic generic clinical management skills for clinical practice, including case-history taking, clinical interaction skills, reporting skills and documentation.",
      "course_syllabus": "Please refer to the course outline",
      "assessment_types": {},
      "feedback_evaluation": "Please refer to the course outline",
      "required_readings": "Please refer to the course outline",
      "recommended_readings": ""
    },
    {
      "subject": "SLPA",
      "course_code": "5301",
      "title": "Work Integrated Learning and Clinical Practice I",
      "credits": "1.00",
      "terms": [
        {
          "term_code": "2430",
          "term_name": "2026-27 Term 2",
          "schedule": [
            {
              "section": "-P01-PRA (3636)",
              "meetings": [
                {
                  "time": "TBA",
                  "location": "No Room Required",
                  "instructor": "Professor Valerie Jane PEREIRA",
                  "dates": "04/01/2027 - 05/04/2027"
                }
              ],
              "availability": {
                "capacity": "63",
                "enrolled": "62",
                "waitlist_capacity": "0",
                "waitlist_total": "0",
                "available_seats": "1",
                "status": "Open"
              },
              "class_attributes": "Cantonese and English"
            }
          ]
        }
      ],
      "description": "The course is designed to provide students with experiential learning for them to develop the required clinical skills in managing clients with various communication disorders. Students will be trained to manage, under supervision, paediatric and adult clients in various settings including clinics, schools, health care organizations, and hospitals.",
      "enrollment_requirement": "Pre-requisite: SLPA5201, SLPA5205, SLPA5207, SLPA5300\nFor students in MSc Speech-Language Pathology",
      "course_attributes": "",
      "academic_career": "Postgraduate - Taught",
      "grading_basis": "Pass/Not Pass",
      "component": "Practicum",
      "campus": "Main Campus",
      "academic_group": "Div of ORL & Commn Science",
      "academic_org": "Div of ORL & Commn Science",
      "learning_outcomes": "Upon completion of this course, students will be able to identify appropriate assessment procedure(s) and assessment components and apply the relevant analyses to children's speech.",
      "course_syllabus": "Please refer to the course outline",
      "assessment_types": {},
      "feedback_evaluation": "Please refer to the course outline",
      "required_readings": "Please refer to the course outline",
      "recommended_readings": ""
    },
    {
      "subject": "SLPA",
      "course_code": "5302",
      "title": "Work Integrated Learning and Clinical Practice II",
      "credits": "2.00",
      "terms": [
        {
          "term_code": "2450",
          "term_name": "2026-27 Summer Session",
          "schedule": [
            {
              "section": "-P01-PRA (1135)",
              "meetings": [
                {
                  "time": "TBA",
                  "location": "No Room Required",
                  "instructor": "Professor Valerie Jane PEREIRA",
                  "dates": "26/04/2027 - 26/07/2027"
                }
              ],
              "availability": {
                "capacity": "63",
                "enrolled": "62",
                "waitlist_capacity": "0",
                "waitlist_total": "0",
                "available_seats": "1",
                "status": "Open"
              },
              "class_attributes": "Cantonese and English"
            }
          ]
        }
      ],
      "description": "The course is designed to provide students with experiential learning for them to develop the required clinical skills in managing clients with various communication disorders. Students will be trained to manage, under supervision, paediatric and adult clients in various settings including clinics, schools, health care organizations, and hospitals.",
      "enrollment_requirement": "Pre-requisite: SLPA5203, SLPA5204, SLPA5206, SLPA5210, SLPA5300, SLPA5301\nFor students in MSc Speech-Language Pathology",
      "course_attributes": "",
      "academic_career": "Postgraduate - Taught",
      "grading_basis": "Pass/Not Pass",
      "component": "Practicum",
      "campus": "Main Campus",
      "academic_group": "Div of ORL & Commn Science",
      "academic_org": "Div of ORL & Commn Science",
      "learning_outcomes": "Upon completion of this course, students will be able to discuss the different ways of identifying appropriate goals and identify the most appropriate intervention approach based on the available evidence-base.",
      "course_syllabus": "Please refer to the course outline",
      "assessment_types": {},
      "feedback_evaluation": "Please refer to the course outline",
      "required_readings": "Please refer to the course outline",
      "recommended_readings": ""
    },
    {
      "subject": "SLPA",
      "course_code": "5401",
      "title": "Phonetics and Phonology for Speech-Language-Pathology",
      "credits": "3.00",
      "terms": [
        {
          "term_code": "2420",
          "term_name": "2026-27 Term 1",
          "schedule": [
            {
              "section": "--LEC (2322)",
              "meetings": [
                {
                  "time": "Fr 1:30PM - 4:15PM",
                  "location": "Hui Yeung Shing Bldg G04",
                  "instructor": "Dr. YU Shing",
                  "dates": "11/9, 18/9, 25/9, 2/10, 9/10, 16/10, 23/10, 30/10, 6/11, 13/11, 20/11, 27/11, 4/12, 11/12"
                }
              ],
              "availability": {
                "capacity": "63",
                "enrolled": "62",
                "waitlist_capacity": "0",
                "waitlist_total": "0",
                "available_seats": "1",
                "status": "Open"
              },
              "class_attributes": "English only"
            }
          ]
        }
      ],
      "description": "This course introduces students to a unified approach to language as a complex structure represented in the minds of its speakers. Empirical linguistic data will be drawn across languages to enable students to understand the intimate relation between language and the human mind. On the basis of this understanding, students are led to explore the core areas of linguistics. The exploration starts with natural language sound systems and phonological components of grammar. These will be explained with basic concepts and recent theoretical advances in linguistic studies alongside new findings in language acquisition. Students will learn to apply these concepts and ideas to tackle linguistic problems.",
      "enrollment_requirement": "For students in MSc Speech-Language Pathology",
      "course_attributes": "",
      "academic_career": "Postgraduate - Taught",
      "grading_basis": "Graded",
      "component": "Lecture",
      "campus": "Main Campus",
      "academic_group": "Div of ORL & Commn Science",
      "academic_org": "Div of ORL & Commn Science",
      "learning_outcomes": "Upon completion of this course, students will be able to:\n1. Classify speech sounds according to articulatory criteria;\n2. Use phonetic transcription to learn the pronunciation of new words;\n3. Recognize and analyze the phonological structure of the word;\n4. Be able to apply the phonological concepts into data analysis",
      "course_syllabus": "Please refer to the course outline",
      "assessment_types": {},
      "feedback_evaluation": "Please refer to the course outline",
      "required_readings": "Please refer to the course outline",
      "recommended_readings": ""
    },
    {
      "subject": "SLPA",
      "course_code": "5402",
      "title": "Syntax and Semantics for Speech-Language-Pathology",
      "credits": "3.00",
      "terms": [
        {
          "term_code": "2430",
          "term_name": "2026-27 Term 2",
          "schedule": [
            {
              "section": "--LEC (2292)",
              "meetings": [
                {
                  "time": "We 4:30PM - 7:15PM",
                  "location": "Lady Shaw Bldg LT4",
                  "instructor": "Miss FUNG Hiu Man Cat",
                  "dates": "6/1, 13/1, 20/1, 27/1, 3/2"
                },
                {
                  "time": "We 4:30PM - 7:15PM",
                  "location": "Lady Shaw Bldg LT4",
                  "instructor": "Miss FUNG Hiu Man Cat, \nProfessor LAW Thomas Ka Tung",
                  "dates": "17/2, 24/2, 3/3, 10/3, 17/3, 24/3, 31/3, 7/4, 14/4"
                }
              ],
              "availability": {
                "capacity": "63",
                "enrolled": "62",
                "waitlist_capacity": "0",
                "waitlist_total": "0",
                "available_seats": "1",
                "status": "Open"
              },
              "class_attributes": "Cantonese and English"
            }
          ]
        }
      ],
      "description": "Taking a modular approach to the language system, this course examines the morphological, semantic and syntactic components of the grammar, as well as the interaction among them. The lectures are intended to provide students with a solid grounding in basic linguistic concepts, which will enable them to tackle linguistic problems, and formulate their own analyses to prepare them for further studies in the discipline. A wide range of data will be discussed to develop students’ sensitivity toward linguistic phenomena with systematic properties in form, meaning and structure.",
      "enrollment_requirement": "For students in MSc Speech-Language Pathology",
      "course_attributes": "",
      "academic_career": "Postgraduate - Taught",
      "grading_basis": "Graded",
      "component": "Lecture",
      "campus": "Main Campus",
      "academic_group": "Div of ORL & Commn Science",
      "academic_org": "Div of ORL & Commn Science",
      "learning_outcomes": "Upon completion of this course, students will be able to:\n1. Develop sensitivity toward language phenomena with systematic properties in form, meaning and structure.\n2. Attain an understanding that individual languages are specific realizations of Universal Grammar.\n3. Build foundations in syntax (e.g. constituent structure and basic syntactic operations motivated by morphology and semantics) and semantics (e.g. predicate-argument, reference, tense~aspect, proposition), and their interfaces (through morphology), to pave the way for further studies in the program.\n4. Gain basic problem solving and analytical skills in the above areas to facilitate studies in more advanced courses.",
      "course_syllabus": "Please refer to the course outline",
      "assessment_types": {},
      "feedback_evaluation": "Please refer to the course outline",
      "required_readings": "Please refer to the course outline",
      "recommended_readings": ""
    },
    {
      "subject": "SLPA",
      "course_code": "5403",
      "title": "Language Acquisition for Speech-Language-Pathology",
      "credits": "3.00",
      "terms": [
        {
          "term_code": "2420",
          "term_name": "2026-27 Term 1",
          "schedule": [
            {
              "section": "--LEC (1206)",
              "meetings": [
                {
                  "time": "Fr 9:30AM - 12:15PM",
                  "location": "Hui Yeung Shing Bldg G04",
                  "instructor": "Miss HU Yunyi",
                  "dates": "11/9, 18/9, 25/9, 2/10, 9/10, 16/10, 23/10, 30/10, 6/11, 13/11, 20/11, 27/11, 4/12"
                }
              ],
              "availability": {
                "capacity": "63",
                "enrolled": "31",
                "waitlist_capacity": "0",
                "waitlist_total": "0",
                "available_seats": "32",
                "status": "Open"
              },
              "class_attributes": "Cantonese and English"
            }
          ]
        }
      ],
      "description": "The acquisition of first language by children has been considered a remarkable feat. How do children accomplish this feat so rapidly and effortlessly? What are the stages they go through in mastering the different aspects of language? What does the development of language in children tell us about the human language faculty? These questions will be examined in light of modern linguistic theory, and nativist and interactionist accounts will be compared. Topics in second language acquisition will also be covered. Questions such as how interlanguage grammars develop in adults and the role of the mother tongue in the construction of interlanguage grammar will be addressed.",
      "enrollment_requirement": "For students in MSc Speech-Language Pathology",
      "course_attributes": "",
      "academic_career": "Postgraduate - Taught",
      "grading_basis": "Graded",
      "component": "Lecture",
      "campus": "Main Campus",
      "academic_group": "Div of ORL & Commn Science",
      "academic_org": "Div of ORL & Commn Science",
      "learning_outcomes": "Upon completion of this course, students will be able to understand:\n1. The nature of language and its acquisition by humans and primates.\n2. The central issues involved in language acquisition inclusive of nature versus nurture, language attainment, cross-linguistic influence, linguistic evidence and the nature of input, as well as linguistic processing.\n3. Language phenomena under exceptional circumstances involving language disorder and language attrition.",
      "course_syllabus": "Please refer to the course outline",
      "assessment_types": {},
      "feedback_evaluation": "Please refer to the course outline",
      "required_readings": "Please refer to the course outline",
      "recommended_readings": ""
    },
    {
      "subject": "SLPA",
      "course_code": "5602",
      "title": "Special Topics in Speech-Language-Pathology",
      "credits": "3.00",
      "terms": [
        {
          "term_code": "2430",
          "term_name": "2026-27 Term 2",
          "schedule": [
            {
              "section": "A-LEC (2432)",
              "meetings": [
                {
                  "time": "Sa 9:00AM - 12:00PM",
                  "location": "Esther Lee Bldg 302",
                  "instructor": "Professor LUK Sau Ha",
                  "dates": "9/1, 16/1, 23/1, 30/1"
                },
                {
                  "time": "Sa 9:00AM - 12:00PM",
                  "location": "Esther Lee Bldg 302",
                  "instructor": "Professor LUK Sau Ha",
                  "dates": "13/2, 20/2, 27/2, 6/3, 13/3, 20/3"
                },
                {
                  "time": "Sa 9:00AM - 12:00PM",
                  "location": "Esther Lee Bldg 302",
                  "instructor": "Professor LUK Sau Ha",
                  "dates": "3/4, 10/4, 17/4"
                }
              ],
              "availability": {
                "capacity": "65",
                "enrolled": "0",
                "waitlist_capacity": "0",
                "waitlist_total": "0",
                "available_seats": "65",
                "status": "Open"
              },
              "class_attributes": "Cantonese and English"
            },
            {
              "section": "B-LEC (2430)",
              "meetings": [
                {
                  "time": "Mo 6:30PM - 9:15PM",
                  "location": "Esther Lee Bldg 403",
                  "instructor": "Staff",
                  "dates": "4/1, 11/1, 18/1, 25/1, 1/2"
                },
                {
                  "time": "Mo 6:30PM - 9:15PM",
                  "location": "Esther Lee Bldg 403",
                  "instructor": "Staff",
                  "dates": "15/2, 22/2, 1/3, 8/3, 15/3, 22/3"
                },
                {
                  "time": "Mo 6:30PM - 9:15PM",
                  "location": "TBA",
                  "instructor": "Staff",
                  "dates": "12/4, 19/4"
                }
              ],
              "availability": {
                "capacity": "50",
                "enrolled": "0",
                "waitlist_capacity": "0",
                "waitlist_total": "0",
                "available_seats": "50",
                "status": "Open"
              },
              "class_attributes": "Cantonese and English"
            },
            {
              "section": "C-LEC (2431)",
              "meetings": [
                {
                  "time": "We 6:30PM - 9:15PM",
                  "location": "Lee Shau Kee Archi Bldg G04",
                  "instructor": "Staff",
                  "dates": "6/1, 13/1, 20/1, 27/1, 3/2"
                },
                {
                  "time": "We 6:30PM - 9:15PM",
                  "location": "Lee Shau Kee Archi Bldg G04",
                  "instructor": "Staff",
                  "dates": "17/2, 24/2, 3/3, 10/3, 17/3, 24/3, 31/3, 7/4"
                }
              ],
              "availability": {
                "capacity": "50",
                "enrolled": "0",
                "waitlist_capacity": "0",
                "waitlist_total": "0",
                "available_seats": "50",
                "status": "Open"
              },
              "class_attributes": "Cantonese and English"
            }
          ]
        }
      ],
      "description": "This course will focus on specific topics in speech-language pathology that are not covered in the regular course offering. These topics will reflect academic needs/interests and faculty expertise. Students are allowed to take this course more than once, and gain the units each time they pass the course. However, students cannot take the course under the same topic twice.",
      "enrollment_requirement": "For students in MSc Speech-Language Pathology and BA Bimodal Bilingual Studies",
      "course_attributes": "",
      "academic_career": "Postgraduate - Taught",
      "grading_basis": "Graded",
      "component": "Lecture",
      "campus": "Main Campus",
      "academic_group": "Div of ORL & Commn Science",
      "academic_org": "Div of ORL & Commn Science",
      "learning_outcomes": "Upon completion of the course, students are expected to achieve the learning goals stated by the instructor who will be an expert in the course topic.",
      "course_syllabus": "Please refer to the course outline",
      "assessment_types": {},
      "feedback_evaluation": "Please refer to the course outline",
      "required_readings": "Please refer to the course outline",
      "recommended_readings": ""
    }
  ]
}
